api_tester_upload_test/__init__.py
api_tester_upload_test/api_helper.py
api_tester_upload_test/api_tester_upload_test_client.py
api_tester_upload_test/configuration.py
api_tester_upload_test/decorators.py
api_tester_upload_test/controllers/__init__.py
api_tester_upload_test/controllers/bad_ssl_controller.py
api_tester_upload_test/controllers/base_controller.py
api_tester_upload_test/exceptions/__init__.py
api_tester_upload_test/exceptions/api_exception.py
api_tester_upload_test/http/__init__.py
api_tester_upload_test/http/http_call_back.py
api_tester_upload_test/http/http_client.py
api_tester_upload_test/http/http_context.py
api_tester_upload_test/http/http_method_enum.py
api_tester_upload_test/http/http_request.py
api_tester_upload_test/http/http_response.py
api_tester_upload_test/http/requests_client.py
api_tester_upload_test/models/__init__.py
tests/__init__.py
tests/http_response_catcher.py
tests/test_helper.py
tests/controllers/__init__.py
tests/controllers/controller_test_base.py
tests/controllers/test_bad_ssl_controller.py
api_tester_upload_test-1.1.73.dist-info/LICENSE
api_tester_upload_test-1.1.73.dist-info/METADATA
api_tester_upload_test-1.1.73.dist-info/WHEEL
api_tester_upload_test-1.1.73.dist-info/top_level.txt
api_tester_upload_test-1.1.73.dist-info/RECORD
